nonebot_plugin_value/__init__.py
nonebot_plugin_value/_cache.py
nonebot_plugin_value/action_type.py
nonebot_plugin_value/config.py
nonebot_plugin_value/dump_tools.py
nonebot_plugin_value/exception.py
nonebot_plugin_value/repository.py
nonebot_plugin_value/uuid_lib.py
nonebot_plugin_value/api/api_balance.py
nonebot_plugin_value/api/api_currency.py
nonebot_plugin_value/api/api_transaction.py
nonebot_plugin_value/api/executor.py
nonebot_plugin_value/api/depends/data_classes.py
nonebot_plugin_value/api/depends/factory.py
nonebot_plugin_value/hook/context.py
nonebot_plugin_value/hook/exception.py
nonebot_plugin_value/hook/hooks_manager.py
nonebot_plugin_value/hook/hooks_type.py
nonebot_plugin_value/migrations/53691b7cf82d_init.py
nonebot_plugin_value/migrations/__init__.py
nonebot_plugin_value/migrations/f3fc1c3ec51d_fix_delete.py
nonebot_plugin_value/models/balance.py
nonebot_plugin_value/models/currency.py
nonebot_plugin_value/models/utils.py
nonebot_plugin_value/pyd_models/action.py
nonebot_plugin_value/pyd_models/balance_pyd.py
nonebot_plugin_value/pyd_models/base_pyd.py
nonebot_plugin_value/pyd_models/currency_pyd.py
nonebot_plugin_value/pyd_models/transaction_pyd.py
nonebot_plugin_value/repositories/account.py
nonebot_plugin_value/repositories/currency.py
nonebot_plugin_value/repositories/transaction.py
nonebot_plugin_value/services/balance.py
nonebot_plugin_value/services/currency.py
nonebot_plugin_value/services/transaction.py
nonebot_plugin_value-0.1.7.dist-info/licenses/LICENSE
nonebot_plugin_value-0.1.7.dist-info/METADATA
nonebot_plugin_value-0.1.7.dist-info/WHEEL
nonebot_plugin_value-0.1.7.dist-info/top_level.txt
nonebot_plugin_value-0.1.7.dist-info/RECORD
