Metadata-Version: 2.4
Name: nonebot-plugin-value
Version: 0.1.7
Summary: Economy API for NoneBot2
Author-email: LiteSuggarDEV <windowserror@163.com>
License:                     GNU GENERAL PUBLIC LICENSE
Requires-Python: <4.0.0,>=3.10
License-File: LICENSE
Requires-Dist: aiofiles>=24.1.0
Requires-Dist: nonebot-plugin-localstore>=0.7.4
Requires-Dist: nonebot-plugin-orm>=0.8.2
Requires-Dist: nonebot2>=2.4.2
Requires-Dist: sqlalchemy>=2.0.41
Dynamic: license-file
